LICENSE.txt
MANIFEST.in
README.rst
setup.cfg
setup.py
neuromwapi/__init__.py
neuromwapi/messages.py
neuromwapi/services.py
neuromwapi.egg-info/PKG-INFO
neuromwapi.egg-info/SOURCES.txt
neuromwapi.egg-info/dependency_links.txt
neuromwapi.egg-info/requires.txt
neuromwapi.egg-info/top_level.txt