Metadata-Version: 1.1
Name: neuromwapi
Version: 0.1.0
Summary: Neurochain masternode-worker P2P API SDK
Home-page: https://github.com/neurochain/neuroapi
Author: Dr Maxim Orlovsky
Author-email: dr.orlovsky@gmail.com
License: MIT
Keywords: blockchain p2p api neurochain
Platform: UNKNOWN
Classifier: Development Status :: 3 - Alpha
Classifier: Intended Audience :: Developers
Classifier: Topic :: Scientific/Engineering :: Artificial Intelligence
Classifier: Topic :: Software Development :: Libraries
Classifier: License :: OSI Approved :: MIT License
Classifier: Programming Language :: Python :: 2
Classifier: Programming Language :: Python :: 2.7
Classifier: Programming Language :: Python :: 3
Classifier: Programming Language :: Python :: 3.3
Classifier: Programming Language :: Python :: 3.4
Classifier: Programming Language :: Python :: 3.5
